mcp_12306/__init__.py
mcp_12306/__main__.py
mcp_12306/main_12306.py
mcp_12306/server.py
12306_mcp-0.1.7.dist-info/METADATA
12306_mcp-0.1.7.dist-info/WHEEL
12306_mcp-0.1.7.dist-info/entry_points.txt
12306_mcp-0.1.7.dist-info/RECORD
